currencies/__init__.py
currencies/admin.py
currencies/conf.py
currencies/context_processors.py
currencies/managers.py
currencies/models.py
currencies/urls.py
currencies/utils.py
currencies/views.py
currencies/fixtures/currencies_test.json
currencies/locale/el/LC_MESSAGES/django.po
currencies/locale/es/LC_MESSAGES/django.po
currencies/locale/ru/LC_MESSAGES/django.po
currencies/management/__init__.py
currencies/management/commands/__init__.py
currencies/management/commands/_currencyhandler.py
currencies/management/commands/_currencyiso.py
currencies/management/commands/_currencyiso.xml
currencies/management/commands/_openexchangerates.json
currencies/management/commands/_openexchangerates.py
currencies/management/commands/_openexchangerates_client.py
currencies/management/commands/_yahoofinance.json
currencies/management/commands/_yahoofinance.py
currencies/management/commands/currencies.json
currencies/management/commands/currencies.py
currencies/management/commands/updatecurrencies.py
currencies/migrations/0001_initial.py
currencies/migrations/0002_alter_model.py
currencies/migrations/0003_currency_info.py
currencies/migrations/0004_code_primary.py
currencies/migrations/__init__.py
currencies/templates/currencies/navbar/currency-chooser-bs3fa.html
currencies/templatetags/__init__.py
currencies/templatetags/currency.py
currencies/tests/openexchangerates_client_testing.txt
currencies/tests/oxr_USD.json
currencies/tests/templates/context_processor.html
currencies/tests/templates/context_tag.html
currencies/tests/templates/index.html
django_currencies-0.9.0.dist-info/LICENSE
django_currencies-0.9.0.dist-info/METADATA
django_currencies-0.9.0.dist-info/WHEEL
django_currencies-0.9.0.dist-info/top_level.txt
django_currencies-0.9.0.dist-info/RECORD
